setup.py
dm/__init__.py
dm.zodb.repair.egg-info/PKG-INFO
dm.zodb.repair.egg-info/SOURCES.txt
dm.zodb.repair.egg-info/dependency_links.txt
dm.zodb.repair.egg-info/namespace_packages.txt
dm.zodb.repair.egg-info/not-zip-safe
dm.zodb.repair.egg-info/top_level.txt
dm/zodb/__init__.py
dm/zodb/repair/README.txt
dm/zodb/repair/VERSION.txt
dm/zodb/repair/__init__.py
dm/zodb/repair/recover.py